setup.py
bin/toggl-report
toggl/__init__.py
toggl/api.py
toggl/report.py
toggl/version.py
toggl_api.egg-info/PKG-INFO
toggl_api.egg-info/SOURCES.txt
toggl_api.egg-info/dependency_links.txt
toggl_api.egg-info/requires.txt
toggl_api.egg-info/top_level.txt