Metadata-Version: 1.0
Name: toggl-api
Version: 0.1.1
Summary: API library for toggl.com
Home-page: http://www.github.com/divitu/toggl-api/
Author: Colin von Heuring
Author-email: colin@von.heuri.ng
License: UNKNOWN
Platform: UNKNOWN
